listas.py
main.py
prompt.py
prompt_personagem_ia-0.1.5.dist-info/licenses/LICENSE
prompt_personagem_ia-0.1.5.dist-info/METADATA
prompt_personagem_ia-0.1.5.dist-info/WHEEL
prompt_personagem_ia-0.1.5.dist-info/top_level.txt
prompt_personagem_ia-0.1.5.dist-info/RECORD
