Metadata-Version: 2.4
Name: prompt_personagem_ia
Version: 0.1.5
Summary: Add your description here
Requires-Python: >=3.12
License-File: LICENSE
Dynamic: license-file
